ADLXPybind/__init__.py
ADLXPybind/__init__.pyi
ADLXPybind/_adlx_pybind.cp310-win_amd64.pyd
ADLXPybind/_adlx_pybind.pyi
adlxpybind-1.4.6.dist-info/METADATA
adlxpybind-1.4.6.dist-info/WHEEL
adlxpybind-1.4.6.dist-info/top_level.txt
adlxpybind-1.4.6.dist-info/RECORD
