Metadata-Version: 2.4
Name: ADLXPybind
Version: 1.4.6
Summary: Python bindings for AMD Device Library Extra (ADLX) 1.4
Author-email: sfinktah <sfinktah@github.spamtrak.org>
License: MIT
Project-URL: Homepage, https://github.com/sfinktah/ADLXPybind
Project-URL: Repository, https://github.com/sfinktah/ADLXPybind
Classifier: Programming Language :: Python :: 3
Classifier: Operating System :: Microsoft :: Windows
Requires-Python: >=3.6
Requires-Dist: pybind11>=2.6.0
Requires-Dist: pybind11-stubgen>=0.10.0
